glitch_filter/source/glitch_filter.vhd
library IEEE;
use IEEE.STD_LOGIC_1164.ALL;
USE IEEE.NUMERIC_STD.ALL;

entity glitch_filter is
    Generic (
        FILTER_CYCLES : INTEGER range 1 to (INTEGER'high) := 2;
        OUT_ON_RESET  : STD_LOGIC := '0'
    );
    Port  (
        clk       : in  STD_LOGIC;
        nreset    : in  STD_LOGIC;
        signal_i  : in  STD_LOGIC;
        signal_o  : out STD_LOGIC
    );
end glitch_filter;


architecture Behavioral of glitch_filter is
    constant zeros   : STD_LOGIC_VECTOR( (FILTER_CYCLES - 1) downto 0 ) := ( others => '0' );
    constant ones    : STD_LOGIC_VECTOR( (FILTER_CYCLES - 1) downto 0 ) := ( others => '1' );

    signal samples : STD_LOGIC_VECTOR( (FILTER_CYCLES - 1) downto 0 ) := ( others => OUT_ON_RESET );
    signal filtered : STD_LOGIC := OUT_ON_RESET;

begin

    sampling: process( clk, nreset )
    begin
        if ( nreset = '0' ) then

            samples <= ( others => OUT_ON_RESET );

        elsif ( rising_edge( clk ) ) then

            samples <= signal_i & samples( (FILTER_CYCLES - 1) downto 1 );

        end if;
    end process sampling;


    filtering: process( clk, nreset )
    begin
        if ( nreset = '0' ) then

            filtered <= OUT_ON_RESET;

        elsif ( rising_edge( clk ) ) then

            if ( samples = zeros ) then
                filtered <= '0';
            elsif ( samples = ones ) then
                filtered <= '1';
            else
                filtered <= filtered;
            end if;

        end if;
    end process filtering;

    signal_o <= filtered;
    
end Behavioral;

glitch_filter/testbench/glitch_filter_tb.vhd

library IEEE;
use IEEE.STD_LOGIC_1164.ALL;
USE IEEE.NUMERIC_STD.ALL;

entity glitch_filter_tb is
end glitch_filter_tb;


architecture behav of glitch_filter_tb is

    component glitch_filter is
        Generic (
            FILTER_CYCLES : INTEGER range 1 to (INTEGER'high) := 2;
            OUT_ON_RESET  : STD_LOGIC := '0'
        );
        Port  (
            clk       : in  STD_LOGIC;
            nreset    : in  STD_LOGIC;
            signal_i  : in  STD_LOGIC;
            signal_o  : out STD_LOGIC
        );
    end component;

    -- Clock period definitions
    constant clk_period : TIME := 20 us;

    -- Constants
    constant filter_clk_cnt  : INTEGER := 3;
    constant out_on_reset    : STD_LOGIC := '0';

    -- Input
    signal clk       : STD_LOGIC := '0';
    signal nreset    : STD_LOGIC := '0';
    signal sync_rst  : STD_LOGIC := '0';
    signal signal_i  : STD_LOGIC := '0';

    -- Output
    signal signal_o  : STD_LOGIC := '0';

begin

    uut: glitch_filter
    GENERIC MAP (
        FILTER_CYCLES => filter_clk_cnt,
        OUT_ON_RESET  => out_on_reset
    )
    PORT MAP (
        clk       => clk,
        nreset    => nreset,
        signal_i  => signal_i,
        signal_o  => signal_o
    );


    -- Generate clock
    clk_ref_process: process
    begin
        clk <= '0';
        wait for clk_period / 2;
        clk <= '1';
        wait for clk_period / 2;
    end process clk_ref_process;


    -- Generate reset signal
    reset_gen: process
    begin
        nreset <= '0';
        wait for ( clk_period / 3 ) * 5;
        nreset <= '1';
        wait;
    end process reset_gen;


    -- Generate input signal
    input_gen: process
    begin
        for fil in 5 to 10 loop

            -- signal not filtered
            for ok in 0 to 1 loop
                signal_i <= '1';
                wait for clk_period * ( 3 * filter_clk_cnt );
                signal_i <= '0';
                wait for clk_period * ( 3 * filter_clk_cnt );
            end loop;

            -- signal filtered
            signal_i <= '1';
            wait for ( clk_period / 3 ) * ( fil - filter_clk_cnt );
            signal_i <= '0';
            wait for ( clk_period / 3 ) * ( fil - filter_clk_cnt );

        end loop;

        signal_i <= '0';
        wait;
    end process input_gen;
    
end behav;

rtl/glitch_filter/simulation/glitch_filter_tb.vcd
$date
  Sat Oct  1 18:59:46 2022
$end
$version
  GHDL v0
$end
$timescale
  1 fs
$end
$scope module standard $end
$upscope $end
$scope module textio $end
$upscope $end
$scope module std_logic_1164 $end
$upscope $end
$scope module numeric_std $end
$upscope $end
$scope module glitch_filter_tb $end
$var reg 1 ! clk $end
$var reg 1 " nreset $end
$var reg 1 # sync_rst $end
$var reg 1 $ signal_i $end
$var reg 1 % signal_o $end
$scope module uut $end
$var reg 1 & clk $end
$var reg 1 ' nreset $end
$var reg 1 ( signal_i $end
$var reg 1 ) signal_o $end
$var reg 3 * samples[2:0] $end
$var reg 1 + filtered $end
$upscope $end
$upscope $end
$enddefinitions $end
#0
0!
0"
0#
1$
0%
0&
0'
1(
0)
b000 *
0+
#10000000000
1!
1&
#20000000000
0!
0&
#30000000000
1!
1&
#33333333330
1"
1'
#40000000000
0!
0&
#50000000000
1!
1&
b100 *
#60000000000
0!
0&
#70000000000
1!
1&
b110 *
#80000000000
0!
0&
#90000000000
1!
1&
b111 *
#100000000000
0!
0&
#110000000000
1!
1%
1&
1)
1+
#120000000000
0!
0&
#130000000000
1!
1&
#140000000000
0!
0&
#150000000000
1!
1&
#160000000000
0!
0&
#170000000000
1!
1&
#180000000000
0!
0$
0&
0(
#190000000000
1!
1&
b011 *
#200000000000
0!
0&
#210000000000
1!
1&
b001 *
#220000000000
0!
0&
#230000000000
1!
1&
b000 *
#240000000000
0!
0&
#250000000000
1!
0%
1&
0)
0+
#260000000000
0!
0&
#270000000000
1!
1&
#280000000000
0!
0&
#290000000000
1!
1&
#300000000000
0!
0&
#310000000000
1!
1&
#320000000000
0!
0&
#330000000000
1!
1&
#340000000000
0!
0&
#350000000000
1!
1&
#360000000000
0!
1$
0&
1(
#370000000000
1!
1&
b100 *
#380000000000
0!
0&
#390000000000
1!
1&
b110 *
#400000000000
0!
0&
#410000000000
1!
1&
b111 *
#420000000000
0!
0&
#430000000000
1!
1%
1&
1)
1+
#440000000000
0!
0&
#450000000000
1!
1&
#460000000000
0!
0&
#470000000000
1!
1&
#480000000000
0!
0&
#490000000000
1!
1&
#500000000000
0!
0&
#510000000000
1!
1&
#520000000000
0!
0&
#530000000000
1!
1&
#540000000000
0!
0$
0&
0(
#550000000000
1!
1&
b011 *
#560000000000
0!
0&
#570000000000
1!
1&
b001 *
#580000000000
0!
0&
#590000000000
1!
1&
b000 *
#600000000000
0!
0&
#610000000000
1!
0%
1&
0)
0+
#620000000000
0!
0&
#630000000000
1!
1&
#640000000000
0!
0&
#650000000000
1!
1&
#660000000000
0!
0&
#670000000000
1!
1&
#680000000000
0!
0&
#690000000000
1!
1&
#700000000000
0!
0&
#710000000000
1!
1&
#720000000000
0!
1$
0&
1(
#730000000000
1!
1&
b100 *
#733333333332
0$
0(
#740000000000
0!
0&
#746666666664
1$
1(
#750000000000
1!
1&
b110 *
#760000000000
0!
0&
#770000000000
1!
1&
b111 *
#780000000000
0!
0&
#790000000000
1!
1%
1&
1)
1+
#800000000000
0!
0&
#810000000000
1!
1&
#820000000000
0!
0&
#830000000000
1!
1&
#840000000000
0!
0&
#850000000000
1!
1&
#860000000000
0!
0&
#870000000000
1!
1&
#880000000000
0!
0&
#890000000000
1!
1&
#900000000000
0!
0&
#910000000000
1!
1&
#920000000000
0!
0&
#926666666664
0$
0(
#930000000000
1!
1&
b011 *
#940000000000
0!
0&
#950000000000
1!
1&
b001 *
#960000000000
0!
0&
#970000000000
1!
1&
b000 *
#980000000000
0!
0&
#990000000000
1!
0%
1&
0)
0+
#1000000000000
0!
0&
#1010000000000
1!
1&
#1020000000000
0!
0&
#1030000000000
1!
1&
#1040000000000
0!
0&
#1050000000000
1!
1&
#1060000000000
0!
0&
#1070000000000
1!
1&
#1080000000000
0!
0&
#1090000000000
1!
1&
#1100000000000
0!
0&
#1106666666664
1$
1(
#1110000000000
1!
1&
b100 *
#1120000000000
0!
0&
#1130000000000
1!
1&
b110 *
#1140000000000
0!
0&
#1150000000000
1!
1&
b111 *
#1160000000000
0!
0&
#1170000000000
1!
1%
1&
1)
1+
#1180000000000
0!
0&
#1190000000000
1!
1&
#1200000000000
0!
0&
#1210000000000
1!
1&
#1220000000000
0!
0&
#1230000000000
1!
1&
#1240000000000
0!
0&
#1250000000000
1!
1&
#1260000000000
0!
0&
#1270000000000
1!
1&
#1280000000000
0!
0&
#1286666666664
0$
0(
#1290000000000
1!
1&
b011 *
#1300000000000
0!
0&
#1310000000000
1!
1&
b001 *
#1320000000000
0!
0&
#1330000000000
1!
1&
b000 *
#1340000000000
0!
0&
#1350000000000
1!
0%
1&
0)
0+
#1360000000000
0!
0&
#1370000000000
1!
1&
#1380000000000
0!
0&
#1390000000000
1!
1&
#1400000000000
0!
0&
#1410000000000
1!
1&
#1420000000000
0!
0&
#1430000000000
1!
1&
#1440000000000
0!
0&
#1450000000000
1!
1&
#1460000000000
0!
0&
#1466666666664
1$
1(
#1470000000000
1!
1&
b100 *
#1480000000000
0!
0&
#1486666666662
0$
0(
#1490000000000
1!
1&
b010 *
#1500000000000
0!
0&
#1506666666660
1$
1(
#1510000000000
1!
1&
b101 *
#1520000000000
0!
0&
#1530000000000
1!
1&
b110 *
#1540000000000
0!
0&
#1550000000000
1!
1&
b111 *
#1560000000000
0!
0&
#1570000000000
1!
1%
1&
1)
1+
#1580000000000
0!
0&
#1590000000000
1!
1&
#1600000000000
0!
0&
#1610000000000
1!
1&
#1620000000000
0!
0&
#1630000000000
1!
1&
#1640000000000
0!
0&
#1650000000000
1!
1&
#1660000000000
0!
0&
#1670000000000
1!
1&
#1680000000000
0!
0&
#1686666666660
0$
0(
#1690000000000
1!
1&
b011 *
#1700000000000
0!
0&
#1710000000000
1!
1&
b001 *
#1720000000000
0!
0&
#1730000000000
1!
1&
b000 *
#1740000000000
0!
0&
#1750000000000
1!
0%
1&
0)
0+
#1760000000000
0!
0&
#1770000000000
1!
1&
#1780000000000
0!
0&
#1790000000000
1!
1&
#1800000000000
0!
0&
#1810000000000
1!
1&
#1820000000000
0!
0&
#1830000000000
1!
1&
#1840000000000
0!
0&
#1850000000000
1!
1&
#1860000000000
0!
0&
#1866666666660
1$
1(
#1870000000000
1!
1&
b100 *
#1880000000000
0!
0&
#1890000000000
1!
1&
b110 *
#1900000000000
0!
0&
#1910000000000
1!
1&
b111 *
#1920000000000
0!
0&
#1930000000000
1!
1%
1&
1)
1+
#1940000000000
0!
0&
#1950000000000
1!
1&
#1960000000000
0!
0&
#1970000000000
1!
1&
#1980000000000
0!
0&
#1990000000000
1!
1&
#2000000000000
0!
0&
#2010000000000
1!
1&
#2020000000000
0!
0&
#2030000000000
1!
1&
#2040000000000
0!
0&
#2046666666660
0$
0(
#2050000000000
1!
1&
b011 *
#2060000000000
0!
0&
#2070000000000
1!
1&
b001 *
#2080000000000
0!
0&
#2090000000000
1!
1&
b000 *
#2100000000000
0!
0&
#2110000000000
1!
0%
1&
0)
0+
#2120000000000
0!
0&
#2130000000000
1!
1&
#2140000000000
0!
0&
#2150000000000
1!
1&
#2160000000000
0!
0&
#2170000000000
1!
1&
#2180000000000
0!
0&
#2190000000000
1!
1&
#2200000000000
0!
0&
#2210000000000
1!
1&
#2220000000000
0!
0&
#2226666666660
1$
1(
#2230000000000
1!
1&
b100 *
#2240000000000
0!
0&
#2250000000000
1!
1&
b110 *
#2253333333324
0$
0(
#2260000000000
0!
0&
#2270000000000
1!
1&
b011 *
#2279999999988
1$
1(
#2280000000000
0!
0&
#2290000000000
1!
1&
b101 *
#2300000000000
0!
0&
#2310000000000
1!
1&
b110 *
#2320000000000
0!
0&
#2330000000000
1!
1&
b111 *
#2340000000000
0!
0&
#2350000000000
1!
1%
1&
1)
1+
#2360000000000
0!
0&
#2370000000000
1!
1&
#2380000000000
0!
0&
#2390000000000
1!
1&
#2400000000000
0!
0&
#2410000000000
1!
1&
#2420000000000
0!
0&
#2430000000000
1!
1&
#2440000000000
0!
0&
#2450000000000
1!
1&
#2459999999988
0$
0(
#2460000000000
0!
0&
#2470000000000
1!
1&
b011 *
#2480000000000
0!
0&
#2490000000000
1!
1&
b001 *
#2500000000000
0!
0&
#2510000000000
1!
1&
b000 *
#2520000000000
0!
0&
#2530000000000
1!
0%
1&
0)
0+
#2540000000000
0!
0&
#2550000000000
1!
1&
#2560000000000
0!
0&
#2570000000000
1!
1&
#2580000000000
0!
0&
#2590000000000
1!
1&
#2600000000000
0!
0&
#2610000000000
1!
1&
#2620000000000
0!
0&
#2630000000000
1!
1&
#2639999999988
1$
1(
#2640000000000
0!
0&
#2650000000000
1!
1&
b100 *
#2660000000000
0!
0&
#2670000000000
1!
1&
b110 *
#2680000000000
0!
0&
#2690000000000
1!
1&
b111 *
#2700000000000
0!
0&
#2710000000000
1!
1%
1&
1)
1+
#2720000000000
0!
0&
#2730000000000
1!
1&
#2740000000000
0!
0&
#2750000000000
1!
1&
#2760000000000
0!
0&
#2770000000000
1!
1&
#2780000000000
0!
0&
#2790000000000
1!
1&
#2800000000000
0!
0&
#2810000000000
1!
1&
#2819999999988
0$
0(
#2820000000000
0!
0&
#2830000000000
1!
1&
b011 *
#2840000000000
0!
0&
#2850000000000
1!
1&
b001 *
#2860000000000
0!
0&
#2870000000000
1!
1&
b000 *
#2880000000000
0!
0&
#2890000000000
1!
0%
1&
0)
0+
#2900000000000
0!
0&
#2910000000000
1!
1&
#2920000000000
0!
0&
#2930000000000
1!
1&
#2940000000000
0!
0&
#2950000000000
1!
1&
#2960000000000
0!
0&
#2970000000000
1!
1&
#2980000000000
0!
0&
#2990000000000
1!
1&
#2999999999988
1$
1(
#3000000000000
0!
0&
#3010000000000
1!
1&
b100 *
#3020000000000
0!
0&
#3030000000000
1!
1&
b110 *
#3033333333318
0$
0(
#3040000000000
0!
0&
#3050000000000
1!
1&
b011 *
#3060000000000
0!
0&
#3066666666648
1$
1(
#3070000000000
1!
1&
b101 *
#3080000000000
0!
0&
#3090000000000
1!
1&
b110 *
#3100000000000
0!
0&
#3110000000000
1!
1&
b111 *
#3120000000000
0!
0&
#3130000000000
1!
1%
1&
1)
1+
#3140000000000
0!
0&
#3150000000000
1!
1&
#3160000000000
0!
0&
#3170000000000
1!
1&
#3180000000000
0!
0&
#3190000000000
1!
1&
#3200000000000
0!
0&
#3210000000000
1!
1&
#3220000000000
0!
0&
#3230000000000
1!
1&
#3240000000000
0!
0&
#3246666666648
0$
0(
#3250000000000
1!
1&
b011 *
#3260000000000
0!
0&
#3270000000000
1!
1&
b001 *
#3280000000000
0!
0&
#3290000000000
1!
1&
b000 *
#3300000000000
0!
0&
#3310000000000
1!
0%
1&
0)
0+
#3320000000000
0!
0&
#3330000000000
1!
1&
#3340000000000
0!
0&
#3350000000000
1!
1&
#3360000000000
0!
0&
#3370000000000
1!
1&
#3380000000000
0!
0&
#3390000000000
1!
1&
#3400000000000
0!
0&
#3410000000000
1!
1&
#3420000000000
0!
0&
#3426666666648
1$
1(
#3430000000000
1!
1&
b100 *
#3440000000000
0!
0&
#3450000000000
1!
1&
b110 *
#3460000000000
0!
0&
#3470000000000
1!
1&
b111 *
#3480000000000
0!
0&
#3490000000000
1!
1%
1&
1)
1+
#3500000000000
0!
0&
#3510000000000
1!
1&
#3520000000000
0!
0&
#3530000000000
1!
1&
#3540000000000
0!
0&
#3550000000000
1!
1&
#3560000000000
0!
0&
#3570000000000
1!
1&
#3580000000000
0!
0&
#3590000000000
1!
1&
#3600000000000
0!
0&
#3606666666648
0$
0(
#3610000000000
1!
1&
b011 *
#3620000000000
0!
0&
#3630000000000
1!
1&
b001 *
#3640000000000
0!
0&
#3650000000000
1!
1&
b000 *
#3660000000000
0!
0&
#3670000000000
1!
0%
1&
0)
0+
#3680000000000
0!
0&
#3690000000000
1!
1&
#3700000000000
0!
0&
#3710000000000
1!
1&
#3720000000000
0!
0&
#3730000000000
1!
1&
#3740000000000
0!
0&
#3750000000000
1!
1&
#3760000000000
0!
0&
#3770000000000
1!
1&
#3780000000000
0!
0&
#3786666666648
1$
1(
#3790000000000
1!
1&
b100 *
#3800000000000
0!
0&
#3810000000000
1!
1&
b110 *
#3820000000000
0!
0&
#3826666666644
0$
0(
#3830000000000
1!
1&
b011 *
#3840000000000
0!
0&
#3850000000000
1!
1&
b001 *
#3860000000000
0!
0&
#3866666666640
1$
1(
#3870000000000
1!
1&
b100 *
#3880000000000
0!
0&
#3890000000000
1!
1&
b110 *
#3900000000000
0!
0&
#3910000000000
1!
1&
b111 *
#3920000000000
0!
0&
#3930000000000
1!
1%
1&
1)
1+
#3940000000000
0!
0&
#3950000000000
1!
1&
#3960000000000
0!
0&
#3970000000000
1!
1&
#3980000000000
0!
0&
#3990000000000
1!
1&
#4000000000000
0!
0&
#4010000000000
1!
1&
#4020000000000
0!
0&
#4030000000000
1!
1&
#4040000000000
0!
0&
#4046666666640
0$
0(
#4050000000000
1!
1&
b011 *
#4060000000000
0!
0&
#4070000000000
1!
1&
b001 *
#4080000000000
0!
0&
#4090000000000
1!
1&
b000 *
#4100000000000
0!
0&
#4110000000000
1!
0%
1&
0)
0+
#4120000000000
0!
0&
#4130000000000
1!
1&
#4140000000000
0!
0&
#4150000000000
1!
1&
#4160000000000
0!
0&
#4170000000000
1!
1&
#4180000000000
0!
0&
#4190000000000
1!
1&
#4200000000000
0!
0&
#4210000000000
1!
1&
#4220000000000
0!
0&
#4226666666640
1$
1(
#4230000000000
1!
1&
b100 *
#4240000000000
0!
0&
#4250000000000
1!
1&
b110 *
#4260000000000
0!
0&
#4270000000000
1!
1&
b111 *
#4280000000000
0!
0&
#4290000000000
1!
1%
1&
1)
1+
#4300000000000
0!
0&
#4310000000000
1!
1&
#4320000000000
0!
0&
#4330000000000
1!
1&
#4340000000000
0!
0&
#4350000000000
1!
1&
#4360000000000
0!
0&
#4370000000000
1!
1&
#4380000000000
0!
0&
#4390000000000
1!
1&
#4400000000000
0!
0&
#4406666666640
0$
0(
#4410000000000
1!
1&
b011 *
#4420000000000
0!
0&
#4430000000000
1!
1&
b001 *
#4440000000000
0!
0&
#4450000000000
1!
1&
b000 *
#4460000000000
0!
0&
#4470000000000
1!
0%
1&
0)
0+
#4480000000000
0!
0&
#4490000000000
1!
1&
#4500000000000
0!
0&
#4510000000000
1!
1&
#4520000000000
0!
0&
#4530000000000
1!
1&
#4540000000000
0!
0&
#4550000000000
1!
1&
#4560000000000
0!
0&
#4570000000000
1!
1&
#4580000000000
0!
0&
#4586666666640
1$
1(
#4590000000000
1!
1&
b100 *
#4600000000000
0!
0&
#4610000000000
1!
1&
b110 *
#4620000000000
0!
0&
#4630000000000
1!
1&
b111 *
#4633333333302
0$
0(
#4640000000000
0!
0&
#4650000000000
1!
1%
1&
1)
b011 *
1+
#4660000000000
0!
0&
#4670000000000
1!
1&
b001 *
#4679999999964
#4680000000000
0!
0&
#4690000000000
1!
1&
b000 *
#4700000000000
0!
0&
#4710000000000
1!
0%
1&
0)
0+
